cue_sdk/__init__.py
cue_sdk/api.py
cue_sdk/enumerations.py
cue_sdk/exceptions.py
cue_sdk/structures.py
cue_sdk-2.1.0.dist-info/DESCRIPTION.rst
cue_sdk-2.1.0.dist-info/METADATA
cue_sdk-2.1.0.dist-info/RECORD
cue_sdk-2.1.0.dist-info/WHEEL
cue_sdk-2.1.0.dist-info/metadata.json
cue_sdk-2.1.0.dist-info/top_level.txt
