Metadata-Version: 2.0
Name: cue-sdk
Version: 2.1.0
Summary: Python wrapper for the CUE SDK
Home-page: UNKNOWN
Author: 10se1ucgo
Author-email: the10se1ucgo@gmail.com
License: Apache License, Version 2.0
